clsl_01/__init__.py
clsl_01/main.py
clsl_01-1572753770.dist-info/METADATA
clsl_01-1572753770.dist-info/WHEEL
clsl_01-1572753770.dist-info/top_level.txt
clsl_01-1572753770.dist-info/RECORD
